LICENSE
MANIFEST.in
README.rst
setup.py
django_upwork_auth/__init__.py
django_upwork_auth/backends.py
django_upwork_auth/models.py
django_upwork_auth/settings.py
django_upwork_auth/tests.py
django_upwork_auth/urls.py
django_upwork_auth/utils.py
django_upwork_auth/views.py
django_upwork_auth.egg-info/PKG-INFO
django_upwork_auth.egg-info/SOURCES.txt
django_upwork_auth.egg-info/dependency_links.txt
django_upwork_auth.egg-info/top_level.txt